README.md
setup.py
prepack/__init__.py
prepack.egg-info/PKG-INFO
prepack.egg-info/SOURCES.txt
prepack.egg-info/dependency_links.txt
prepack.egg-info/not-zip-safe
prepack.egg-info/requires.txt
prepack.egg-info/top_level.txt